Metadata-Version: 2.1
Name: dora-search
Version: 0.1.12
Summary: Easy grid searches for ML.
Home-page: https://github.com/facebookresearch/dora
Author: Alexandre Défossez
Author-email: defossez@fb.com
License: MIT
Platform: UNKNOWN
Classifier: License :: OSI Approved :: MIT License
Classifier: Topic :: Scientific/Engineering :: Artificial Intelligence
Requires-Python: >=3.7.0
Provides-Extra: dev
